regorus-0.1.0.dist-info/METADATA
regorus-0.1.0.dist-info/WHEEL
regorus/__init__.py
regorus/regorus.cpython-311-x86_64-linux-gnu.so
regorus-0.1.0.dist-info/RECORD
